doc_datatypes/__init__.py
doc_datatypes/datatypes.py
doc_datatypes/mutable_datatypes.py
tests/__init__.py
tests/test_datatypes.py
tests/test_mutable_datatypes.py
doc_datatypes-0.0.6.dist-info/METADATA
doc_datatypes-0.0.6.dist-info/WHEEL
doc_datatypes-0.0.6.dist-info/top_level.txt
doc_datatypes-0.0.6.dist-info/RECORD
