Metadata-Version: 2.1
Name: doc-datatypes
Version: 0.0.6
Summary: Dict with documentation _-_
Home-page: https://github.com/Kel0/doc_datatypes
Author: Example Author
Author-email: rickeyfsimple@example.com
License: UNKNOWN
Platform: UNKNOWN
Classifier: Programming Language :: Python :: 3
Requires-Python: >=3.7
